Metadata-Version: 2.1
Name: momo-data-validation-service
Version: 1.2.0
Summary: A package to enable easy data validation
Home-page: https://glab.mservice.io/ai-data-platform/uncategorized-projects/professional-services-data-validator
Author: Nguyen Thuy Dung
Author-email: dung.nguyen24@mservice.com.vn
Classifier: Development Status :: 3 - Alpha
Classifier: License :: OSI Approved :: Apache Software License
Classifier: Programming Language :: Python
Classifier: Programming Language :: Python :: 3.8
Classifier: Programming Language :: Python :: 3.9
Classifier: Programming Language :: Python :: 3.10
Classifier: Operating System :: OS Independent
Requires-Python: >=3.8
License-File: LICENSE
Requires-Dist: attrs ==23.1.0
Requires-Dist: grpcio ==1.62.1
Requires-Dist: lazy-object-proxy ==1.9.0
Requires-Dist: marshmallow ==3.19.0
Requires-Dist: fsspec >=2022.8.2
Requires-Dist: google-api-python-client ==2.91.0
Requires-Dist: ibis-framework ==5.1.0
Requires-Dist: impyla ==0.18.0
Requires-Dist: SQLAlchemy ==1.4.49
Requires-Dist: PyMySQL ==1.1.0
Requires-Dist: psycopg2-binary ==2.9.6
Requires-Dist: PyYAML ==6.0
Requires-Dist: pandas ==1.5.3
Requires-Dist: proto-plus ==1.22.3
Requires-Dist: pyarrow ==14.0.1
Requires-Dist: pydata-google-auth ==1.8.0
Requires-Dist: google-cloud-bigquery ==3.11.3
Requires-Dist: google-cloud-bigquery-storage ==2.20.0
Requires-Dist: google-cloud-spanner ==3.36.0
Requires-Dist: google-cloud-storage ==2.10.0
Requires-Dist: setuptools >=34.0.0
Requires-Dist: jellyfish ==1.0.0
Requires-Dist: tabulate ==0.9.0
Requires-Dist: Flask ==2.3.2
Requires-Dist: parsy ==2.1
Requires-Dist: google-cloud-secret-manager <=2.15.0
Requires-Dist: ibis-framework[trino]
Requires-Dist: trino
Requires-Dist: wheel
Provides-Extra: apache-airflow
Requires-Dist: 1.10.11 ; extra == 'apache-airflow'
Provides-Extra: pyspark
Requires-Dist: 3.0.0 ; extra == 'pyspark'
